MANIFEST.in
README.rst
VERSION
setup.cfg
setup.py
oopen/__init__.py
oopen/cached_property.py
oopen/oopen.py
oopen.egg-info/PKG-INFO
oopen.egg-info/SOURCES.txt
oopen.egg-info/dependency_links.txt
oopen.egg-info/entry_points.txt
oopen.egg-info/not-zip-safe
oopen.egg-info/top_level.txt