Metadata-Version: 1.1
Name: oopen
Version: 0.1.0-dev
Summary: Object-Oriented File and Path manipulation
Home-page: https://github.com/ajhekman/OOpen
Author: Andrew Hekman
Author-email: ajhekman@gmail.com
License: MIT
Keywords: file path oo
Platform: UNKNOWN
Classifier: Development Status :: 3 - Alpha
Classifier: Intended Audience :: Developers
Classifier: Intended Audience :: System Administrators
Classifier: License :: OSI Approved :: MIT License
Classifier: Topic :: Software Development :: Libraries :: Python Modules
